[
    {
      "name": "Shivam Sharma",
      "father_name": "Hari Sharma",
      "mother_name": "Neetu Sharma",
      "dob": "13 July 2015",
      "adhar_no": "5666757622",
      "blood_group": "A+",
      "address": "Panchsheel Green-2",
      "isActive": "Yes",
      "class": "IV",
      "section": "B",
      "transport": "Yes",
      "Mobile": "7868768783",
      "Id": "A-566"
    },
    {
      "name": "Rahul Kumar",
      "father_name": "Sanjay Kumar",
      "mother_name": "Priya Kumar",
      "dob": "22 August 2014",
      "adhar_no": "3456789123",
      "blood_group": "B-",
      "address": "Saket",
      "isActive": "No",
      "class": "V",
      "section": "C",
      "transport": "No",
      "Mobile": "9876543210",
      "Id": "B-789"
    },
    {
      "name": "Priya Singh",
      "father_name": "Amit Singh",
      "mother_name": "Anita Singh",
      "dob": "7 May 2016",
      "adhar_no": "9876543210",
      "blood_group": "O+",
      "address": "Malviya Nagar",
      "isActive": "Yes",
      "class": "III",
      "section": "A",
      "transport": "Yes",
      "Mobile": "8765432109",
      "Id": "C-123"
    },
    {
      "name": "Ankit Verma",
      "father_name": "Rajesh Verma",
      "mother_name": "Meena Verma",
      "dob": "15 September 2015",
      "adhar_no": "2345678901",
      "blood_group": "AB+",
      "address": "Vasant Kunj",
      "isActive": "Yes",
      "class": "II",
      "section": "D",
      "transport": "No",
      "Mobile": "7654321098",
      "Id": "D-456"
    },
    {
      "name": "Sneha Gupta",
      "father_name": "Alok Gupta",
      "mother_name": "Pooja Gupta",
      "dob": "10 March 2015",
      "adhar_no": "8765432109",
      "blood_group": "A-",
      "address": "Rohini",
      "isActive": "No",
      "class": "VI",
      "section": "A",
      "transport": "Yes",
      "Mobile": "6543210987",
      "Id": "E-789"
    },
    {
      "name": "Ravi Sharma",
      "father_name": "Vinod Sharma",
      "mother_name": "Sunita Sharma",
      "dob": "4 November 2014",
      "adhar_no": "7890123456",
      "blood_group": "B+",
      "address": "Dwarka",
      "isActive": "Yes",
      "class": "I",
      "section": "B",
      "transport": "Yes",
      "Mobile": "5432109876",
      "Id": "F-012"
    },
    {
      "name": "Neha Patel",
      "father_name": "Manoj Patel",
      "mother_name": "Rita Patel",
      "dob": "28 June 2016",
      "adhar_no": "5432109876",
      "blood_group": "O-",
      "address": "Mayur Vihar",
      "isActive": "No",
      "class": "IV",
      "section": "C",
      "transport": "No",
      "Mobile": "4321098765",
      "Id": "G-345"
    },
    {
      "name": "Arun Singh",
      "father_name": "Vijay Singh",
      "mother_name": "Sangeeta Singh",
      "dob": "19 February 2015",
      "adhar_no": "6543210987",
      "blood_group": "AB-",
      "address": "Lajpat Nagar",
      "isActive": "Yes",
      "class": "III",
      "section": "D",
      "transport": "Yes",
      "Mobile": "3210987654",
      "Id": "H-678"
    },
    {
      "name": "Divya Sharma",
      "father_name": "Rakesh Sharma",
      "mother_name": "Kavita Sharma",
      "dob": "9 December 2015",
      "adhar_no": "4321098765",
      "blood_group": "A+",
      "address": "Greater Kailash",
      "isActive": "No",
      "class": "V",
      "section": "A",
      "transport": "Yes",
      "Mobile": "2109876543",
      "Id": "I-901"
    },
    {
      "name": "Mohit Verma",
      "father_name": "Sunil Verma",
      "mother_name": "Nidhi Verma",
      "dob": "25 October 2014",
      "adhar_no": "2109876543",
      "blood_group": "B-",
      "address": "South Extension",
      "isActive": "Yes",
      "class": "VI",
      "section": "B",
      "transport": "No",
      "Mobile": "1098765432",
      "Id": "J-234"
    }
  ]